acrul_toolkit/__init__.py
acrul_toolkit/custom_resources.py
acrul_toolkit/module_loading.py
acrul_toolkit/secretsmanager.py
acru_l_toolkit-0.1.0.dist-info/LICENSE
acru_l_toolkit-0.1.0.dist-info/WHEEL
acru_l_toolkit-0.1.0.dist-info/METADATA
acru_l_toolkit-0.1.0.dist-info/RECORD
