Metadata-Version: 2.1
Name: acru-l-toolkit
Version: 0.1.0
Summary: 
License: MIT
Author: Anthony Almarza
Author-email: anthony.almarza@gmail.com
Requires-Python: >=3.8,<4.0
Classifier: License :: OSI Approved :: MIT License
Classifier: Programming Language :: Python :: 3
Classifier: Programming Language :: Python :: 3.8
Classifier: Programming Language :: Python :: 3.9
Requires-Dist: boto3 (>=1.16.40,<2.0.0)
